libsbmlnetworkeditor/__init__.py
libsbmlnetworkeditor/libsbmlnetworkeditor.0.0.14.dylib
libsbmlnetworkeditor/libsbmlnetworkeditor.0.dylib
libsbmlnetworkeditor/libsbmlnetworkeditor.dylib
libsbmlnetworkeditor/libsbmlnetworkeditor.py
libsbmlnetworkeditor/dependencies/libsbml.5.20.2.dylib
libsbmlnetworkeditor/dependencies/libsbml.5.dylib
libsbmlnetworkeditor/dependencies/libsbml.dylib
libsbmlnetworkeditor-0.0.14.dist-info/METADATA
libsbmlnetworkeditor-0.0.14.dist-info/WHEEL
libsbmlnetworkeditor-0.0.14.dist-info/top_level.txt
libsbmlnetworkeditor-0.0.14.dist-info/RECORD
